rerate/__init__.py
rerate/abstract_store.py
rerate/decorator.py
rerate/dictionary_store.py
rerate/exceptions.py
rerate/rate_limit.py
rerate/redis_store.py
rerate/timestamp_typedef.py
rerate-0.0.2.dist-info/METADATA
rerate-0.0.2.dist-info/WHEEL
rerate-0.0.2.dist-info/licenses/LICENSE
rerate-0.0.2.dist-info/RECORD
