Metadata-Version: 2.1
Name: rerate
Version: 0.0.2
Summary: Flexible, easy to use rate limiter
Project-URL: Homepage, https://github.com/patrickzbhe/rerate
Project-URL: Issues, https://github.com/patrickzbhe/rerate/issues
Author-email: Patrick He <patrick.zebing.he@gmail.com>
License-File: LICENSE
Classifier: License :: OSI Approved :: MIT License
Classifier: Programming Language :: Python :: 3
Requires-Python: >=3.11
